zipapp_utils/__init__.py
zipapp_utils/api.py
zipapp_utils/arg_handlers.py
zipapp_utils/cli.py
zipapp_utils/config.py
zipapp_utils/filters.py
zipapp_utils/parsers_util.py
zipapp_utils/templates/__main__.jinja.py
zipapp_utils/templates/bundle_and_run_pyz.jinja.sh
zipapp_utils/templates.py
zipapp_utils/utils.py
zipapp_utils-0.3.1.dist-info/entry_points.txt
zipapp_utils-0.3.1.dist-info/LICENSE.cpython
zipapp_utils-0.3.1.dist-info/LICENSE.jinja2-cli
zipapp_utils-0.3.1.dist-info/LICENSE
zipapp_utils-0.3.1.dist-info/WHEEL
zipapp_utils-0.3.1.dist-info/METADATA
zipapp_utils-0.3.1.dist-info/RECORD
