Metadata-Version: 2.1
Name: zipapp-utils
Version: 0.3.1
Summary: zipapp utilities
Home-page: https://github.com/tddschn/zipapp-utils
License: MIT
Keywords: zipapp,utils
Author: Xinyuan Chen
Author-email: 45612704+tddschn@users.noreply.github.com
Requires-Python: >=3.10,<4.0
Classifier: License :: OSI Approved :: MIT License
Classifier: Programming Language :: Python :: 3
Classifier: Programming Language :: Python :: 3.10
Classifier: Topic :: Utilities
Requires-Dist: Jinja2 (>=3.1.2,<4.0.0)
Requires-Dist: poetry-core[poetry] (>=1.0.8,<2.0.0)
Project-URL: Bug Tracker, https://github.com/tddschn/zipapp-utils/issues
Project-URL: Repository, https://github.com/tddschn/zipapp-utils
